odoo/addons/spreadsheet_oca/README.rst
odoo/addons/spreadsheet_oca/__init__.py
odoo/addons/spreadsheet_oca/__manifest__.py
odoo/addons/spreadsheet_oca/controllers/__init__.py
odoo/addons/spreadsheet_oca/controllers/main.py
odoo/addons/spreadsheet_oca/data/spreadsheet_spreadsheet_import_mode.xml
odoo/addons/spreadsheet_oca/demo/demo_spreadsheet.json
odoo/addons/spreadsheet_oca/demo/spreadsheet_spreadsheet.xml
odoo/addons/spreadsheet_oca/i18n/es.po
odoo/addons/spreadsheet_oca/i18n/fr.po
odoo/addons/spreadsheet_oca/i18n/fr_FR.po
odoo/addons/spreadsheet_oca/i18n/it.po
odoo/addons/spreadsheet_oca/i18n/nl.po
odoo/addons/spreadsheet_oca/i18n/pt.po
odoo/addons/spreadsheet_oca/i18n/spreadsheet_oca.pot
odoo/addons/spreadsheet_oca/i18n/zh_CN.po
odoo/addons/spreadsheet_oca/models/__init__.py
odoo/addons/spreadsheet_oca/models/ir_websocket.py
odoo/addons/spreadsheet_oca/models/spreadsheet_abstract.py
odoo/addons/spreadsheet_oca/models/spreadsheet_oca_revision.py
odoo/addons/spreadsheet_oca/models/spreadsheet_spreadsheet.py
odoo/addons/spreadsheet_oca/models/spreadsheet_spreadsheet_import_mode.py
odoo/addons/spreadsheet_oca/models/spreadsheet_spreadsheet_tag.py
odoo/addons/spreadsheet_oca/readme/CONTRIBUTORS.md
odoo/addons/spreadsheet_oca/readme/DESCRIPTION.md
odoo/addons/spreadsheet_oca/readme/DEVELOP.md
odoo/addons/spreadsheet_oca/readme/USAGE.md
odoo/addons/spreadsheet_oca/security/ir.model.access.csv
odoo/addons/spreadsheet_oca/security/security.xml
odoo/addons/spreadsheet_oca/static/description/icon.png
odoo/addons/spreadsheet_oca/static/description/icon.svg
odoo/addons/spreadsheet_oca/static/description/index.html
odoo/addons/spreadsheet_oca/static/description/o-spreadsheet.png
odoo/addons/spreadsheet_oca/static/description/spreadsheet_create.png
odoo/addons/spreadsheet_oca/static/description/spreadsheet_dynamic_table.gif
odoo/addons/spreadsheet_oca/static/description/spreadsheet_edit.png
odoo/addons/spreadsheet_oca/static/src/spreadsheet/graph_controller.esm.js
odoo_addon_spreadsheet_oca-18.0.1.1.0.2.dist-info/METADATA
odoo_addon_spreadsheet_oca-18.0.1.1.0.2.dist-info/WHEEL
odoo_addon_spreadsheet_oca-18.0.1.1.0.2.dist-info/top_level.txt
odoo_addon_spreadsheet_oca-18.0.1.1.0.2.dist-info/RECORD
